[
  {
		"name": "2009 Station Fire, Arroyo Seco, CA",
		"lat": 34.236638,
		"lng": -118.195305,
		"href": "arroyo_seco/"
	},
  {
    "name": "Bent Creek Experimental Forest, NC",
    "lat": 35.45482,
    "lng": -82.65219,
    "href": "bent_creek/"
  },
  {
    "name": "Chalk Cliffs, CO",
    "lat":  38.732179,
    "lng":  -106.18576,
    "href": "chalk_cliffs/"
  },
  {
		"name": "2009 Station Fire, Dunsmore Canyon, Glendale, CA",
		"lat": 34.261317,
		"lng": -118.241969,
		"href": "dunsmore/"
	},
  {
		"name": "U.S. Highway 50, CA",
    "lat":  38.7775,
    "lng":  -120.4199,
		"href": "hwy50/"
	},
	{
		"name": "Knife Ridge, Elliott State Forest, OR",
		"lat":  43.615277,
		"lng":  -123.93561,
		"href": "knife_ridge/"
	},
	{
		"name": "Millicoma Meander, Elliott State Forest, OR",
		"lat":  43.576,
		"lng":  -123.946,
		"href": "millicoma_meander/"
	},
	{
		"name": "Mooney Gap, Coweeta Experimental Forest, NC",
		"lat": 35.03363,
		"lng": -83.46802,
		"href": "mooneygap/"
	},
  {
    "name": "Poplar Cove, Nantahala National Forest, NC",
    "lat": 35.12211,
    "lng": -83.53866,
    "href": "poplar_cove/"
  },
	{
		"name": "Portland, OR",
		"lat":  45.522,
		"lng":  -122.734,
		"href": "portland/"
	},
	{
		"name": "Seattle Area, WA",
		"lat":  47.54163,
		"lng":  -122.3,
		"href": "seattle/"
	},
	{
		"name": "2013 Springs Fire, Ventura County, CA",
		"lat": 34.196310,
		"lng": -118.982946,
		"href": "springs/"
	}
]
